{
  "id" : "vitalsign",
  "resourceType" : "StructureDefinition",
  "url" : "https://datatools4heart.eu/fhir/schemas/icrc/vitalsign",
  "version" : "latest",
  "name" : "VitalSign",
  "status" : "draft",
  "fhirVersion" : "5.0.0",
  "kind" : "logical",
  "abstract" : false,
  "type" : "VitalSign",
  "baseDefinition" : "http://hl7.org/fhir/StructureDefinition/Element",
  "derivation" : "specialization",
  "differential" : {
    "element" : [ {
      "id" : "VitalSign",
      "path" : "VitalSign",
      "min" : 0,
      "max" : "*",
      "type" : [ {
        "code" : "Element"
      } ]
    }, {
      "id" : "VitalSign.id_vital_sign",
      "path" : "VitalSign.id_vital_sign",
      "min" : 1,
      "max" : "1",
      "type" : [ {
        "code" : "integer",
        "profile" : [ "http://hl7.org/fhir/StructureDefinition/integer" ]
      } ],
      "short" : "Vital sign identifier"
    }, {
      "id" : "VitalSign.id_patient",
      "path" : "VitalSign.id_patient",
      "min" : 1,
      "max" : "1",
      "type" : [ {
        "code" : "integer",
        "profile" : [ "http://hl7.org/fhir/StructureDefinition/integer" ]
      } ],
      "short" : "Patient identifier"
    }, {
      "id" : "VitalSign.id_encounter",
      "path" : "VitalSign.id_encounter",
      "min" : 1,
      "max" : "1",
      "type" : [ {
        "code" : "integer",
        "profile" : [ "http://hl7.org/fhir/StructureDefinition/integer" ]
      } ],
      "short" : "Encounter identifier"
    }, {
      "id" : "VitalSign.id_department",
      "path" : "VitalSign.id_department",
      "min" : 0,
      "max" : "1",
      "type" : [ {
        "code" : "integer",
        "profile" : [ "http://hl7.org/fhir/StructureDefinition/integer" ]
      } ],
      "short" : "Department identifier"
    }, {
      "id" : "VitalSign.efective_datetime",
      "path" : "VitalSign.efective_datetime",
      "min" : 0,
      "max" : "1",
      "type" : [ {
        "code" : "dateTime",
        "profile" : [ "http://hl7.org/fhir/StructureDefinition/dateTime" ]
      } ],
      "short" : "Date and time of the vital sign measurement"
    }, {
      "id" : "VitalSign.weight",
      "path" : "VitalSign.weight",
      "min" : 0,
      "max" : "1",
      "type" : [ {
        "code" : "integer",
        "profile" : [ "http://hl7.org/fhir/StructureDefinition/integer" ]
      } ],
      "short" : "Body weight"
    }, {
      "id" : "VitalSign.height",
      "path" : "VitalSign.height",
      "min" : 0,
      "max" : "1",
      "type" : [ {
        "code" : "integer",
        "profile" : [ "http://hl7.org/fhir/StructureDefinition/integer" ]
      } ],
      "short" : "Body height"
    }, {
      "id" : "VitalSign.systolic_pressure",
      "path" : "VitalSign.systolic_pressure",
      "min" : 0,
      "max" : "1",
      "type" : [ {
        "code" : "integer",
        "profile" : [ "http://hl7.org/fhir/StructureDefinition/integer" ]
      } ],
      "short" : "Systolic blood pressure"
    }, {
      "id" : "VitalSign.diastolic_pressure",
      "path" : "VitalSign.diastolic_pressure",
      "min" : 0,
      "max" : "1",
      "type" : [ {
        "code" : "integer",
        "profile" : [ "http://hl7.org/fhir/StructureDefinition/integer" ]
      } ],
      "short" : "Diastolic blood pressure"
    }, {
      "id" : "VitalSign.heart_rate",
      "path" : "VitalSign.heart_rate",
      "min" : 0,
      "max" : "1",
      "type" : [ {
        "code" : "integer",
        "profile" : [ "http://hl7.org/fhir/StructureDefinition/integer" ]
      } ],
      "short" : "Heart rate"
    }, {
      "id" : "VitalSign.respiration",
      "path" : "VitalSign.respiration",
      "min" : 0,
      "max" : "1",
      "type" : [ {
        "code" : "integer",
        "profile" : [ "http://hl7.org/fhir/StructureDefinition/integer" ]
      } ],
      "short" : "Respiration rate"
    }, {
      "id" : "VitalSign.spo2",
      "path" : "VitalSign.spo2",
      "min" : 0,
      "max" : "1",
      "type" : [ {
        "code" : "decimal",
        "profile" : [ "http://hl7.org/fhir/StructureDefinition/decimal" ]
      } ],
      "short" : "Oxygen saturation"
    }, {
      "id" : "VitalSign.body_temperature",
      "path" : "VitalSign.body_temperature",
      "min" : 0,
      "max" : "1",
      "type" : [ {
        "code" : "decimal",
        "profile" : [ "http://hl7.org/fhir/StructureDefinition/decimal" ]
      } ],
      "short" : "Body temperature"
    }, {
      "id" : "VitalSign.nyha",
      "path" : "VitalSign.nyha",
      "min" : 0,
      "max" : "1",
      "type" : [ {
        "code" : "integer",
        "profile" : [ "http://hl7.org/fhir/StructureDefinition/integer" ]
      } ],
      "short" : "NYHA assessment value"
    } ]
  }
}